data_model_router/__init__.py
data_model_router/main.py
data_model_router/utils.py
data_model_router/router/__init__.py
data_model_router/router/create.py
data_model_router/router/delete.py
data_model_router/router/get_by_id.py
data_model_router/router/save.py
data_model_router/router/search.py
datamodel_router-2.1.0.dist-info/METADATA
datamodel_router-2.1.0.dist-info/WHEEL
datamodel_router-2.1.0.dist-info/top_level.txt
datamodel_router-2.1.0.dist-info/RECORD
