Metadata-Version: 2.2
Name: datamodel-router
Version: 2.1.0
Summary: A simple router for data_models
Author-email: Tobias Ahlers <93325697+TobiasAhlers@users.noreply.github.com>
Project-URL: Homepage, https://github.com/TobiasAhlers/DataModel-Router
Project-URL: Issues, https://github.com/TobiasAhlers/DataModel-Router/issues
Classifier: Programming Language :: Python :: 3
Classifier: Operating System :: OS Independent
Requires-Python: >=3.11
Requires-Dist: fastapi
Requires-Dist: datamodel-orm
Provides-Extra: test
Requires-Dist: pytest; extra == "test"
Requires-Dist: pytest-cov; extra == "test"
Requires-Dist: httpx; extra == "test"
Requires-Dist: setuptools; extra == "test"
